.gitignore
.travis.yml
LICENSE
README.md
setup.cfg
setup.py
tox.ini
docs/Makefile
docs/make.bat
docs/source/conf.py
docs/source/index.rst
examples/short.py
examples/simple.py
examples/example_classes/__init__.py
examples/example_classes/car.py
examples/example_classes/driver.py
examples/example_classes/engine.py
examples/example_classes/interfaces.py
examples/example_classes/wheel.py
pyhooker/__init__.py
pyhooker/func_utils.py
pyhooker/loading.py
pyhooker.egg-info/PKG-INFO
pyhooker.egg-info/SOURCES.txt
pyhooker.egg-info/dependency_links.txt
pyhooker.egg-info/requires.txt
pyhooker.egg-info/top_level.txt
pyhooker/tests/__init__.py
pyhooker/tests/classes.py
pyhooker/tests/import_objects.py
pyhooker/tests/test_import.py
pyhooker/tests/test_parameter_injection.py
pyhooker/tests/test_registry.py