Metadata-Version: 1.1
Name: pyhooker
Version: 1.0.1
Summary: Just another python DI library.
Home-page: https://github.com/sighalt/pyhooker
Author: Jakob Rößler
Author-email: roessler@sighalt.de
License: GPL3
Download-URL: https://github.com/sighalt/pyhooker/tarball/1.0.1
Keywords: DI,dependency injection,inversion of control,IOC
Platform: UNKNOWN
Classifier: Development Status :: 5 - Production/Stable
Classifier: Intended Audience :: Developers
Classifier: License :: OSI Approved :: GNU General Public License v3 (GPLv3)
Classifier: Topic :: Software Development
